econml/_ortho_learner.py
econml/_rlearner.py
econml/_tree_exporter.py
econml/automated_ml.py
econml/bootstrap.py
econml/cate_estimator.py
econml/cate_interpreter.py
econml/causal_forest.py
econml/causal_tree.py
econml/deepiv.py
econml/dgp.py
econml/dml.py
econml/drlearner.py
econml/inference.py
econml/metalearners.py
econml/ortho_forest.py
econml/ortho_iv.py
econml/two_stage_least_squares.py
econml/unit_tests.py
econml/utilities.py
econml/data/dgps.py
econml/data/ihdp/example.csv
econml/data/ihdp/example_full.csv
econml/data/ihdp/sim.csv
econml/sklearn_extensions/ensemble.py
econml/sklearn_extensions/linear_model.py
econml/sklearn_extensions/model_selection.py
econml/tests/test_automated_ml.py
econml/tests/test_bootstrap.py
econml/tests/test_cate_interpreter.py
econml/tests/test_deepiv.py
econml/tests/test_dml.py
econml/tests/test_dominicks.py
econml/tests/test_drlearner.py
econml/tests/test_ensemble.py
econml/tests/test_inference.py
econml/tests/test_linear_model.py
econml/tests/test_metalearners.py
econml/tests/test_notebooks.py
econml/tests/test_orf.py
econml/tests/test_ortho_iv.py
econml/tests/test_ortho_learner.py
econml/tests/test_random_state.py
econml/tests/test_statsmodels.py
econml/tests/test_two_stage_least_squares.py
econml/tests/test_utilities.py
econml/tests/utilities.py
foundry_econml-0.8.1.4.dist-info/LICENSE
foundry_econml-0.8.1.4.dist-info/METADATA
foundry_econml-0.8.1.4.dist-info/WHEEL
foundry_econml-0.8.1.4.dist-info/top_level.txt
foundry_econml-0.8.1.4.dist-info/RECORD
