Metadata-Version: 2.1
Name: foundry-econml
Version: 0.8.1.4
Summary: This package contains several methods for calculating Conditional Average Treatment Effects
Home-page: https://github.com/FoundryAI/EconML
Author: Microsoft Corporation
License: MIT
Project-URL: Bug Tracker, https://github.com/FoundryAI/EconML/Issues
Project-URL: Source Code, https://github.com/FoundryAI/EconML
Project-URL: Documentation, https://econml.azurewebsites.net/
Keywords: treatment-effect
Platform: UNKNOWN
Classifier: Programming Language :: Python :: 3.6
Classifier: Programming Language :: Python :: 3.7
Classifier: Programming Language :: Python :: 3.8
Classifier: License :: OSI Approved :: MIT License
Classifier: Operating System :: OS Independent
Requires-Dist: numpy
Requires-Dist: scipy (!=1.4.0)
Requires-Dist: scikit-learn (>0.21.0)
Requires-Dist: keras (<2.4)
Requires-Dist: sparse
Requires-Dist: tensorflow (<2.3,>1.10)
Requires-Dist: joblib (>=0.13.0)
Requires-Dist: numba (!=0.42.1)
Requires-Dist: statsmodels (>=0.9)
Requires-Dist: graphviz
Requires-Dist: matplotlib
Requires-Dist: pandas (<1.1)
Provides-Extra: automl
Requires-Dist: azureml-sdk[automl,explain] (==1.0.83) ; extra == 'automl'
Requires-Dist: azure-cli ; extra == 'automl'
